{
  "id": "ai-companion",
  "title": "NPC Autopilot v3.6.0",
  "description": "Foundry VTT NPC combat autopilot. v3.6.0: Archetype-aware tactics (assassin, bruiser, controller, healer, skirmisher, sniper, caster, flying), tactical target priority, positioning (charge/flank/mid/hang_back), ally healing, and class/monster trait detection. v3.5.8: ChatMessage fix.",
  "version": "3.6.0",
  "authors": [
    {
      "name": "Steve"
    }
  ],
  "compatibility": {
    "minimum": "11",
    "verified": "14",
    "maximum": "14"
  },
  "esmodules": [
    "scripts/npc-autopilot.js"
  ],
  "styles": [
    "styles/npc-autopilot.css"
  ],
  "languages": [
    {
      "lang": "en",
      "name": "English",
      "path": "lang/en.json"
    }
  ],
  "manifest": "https://raw.githubusercontent.com/darrenmcguff-GRC/ai-companion/main/module.json",
  "download": "https://raw.githubusercontent.com/darrenmcguff-GRC/ai-companion/main/ai-companion.zip",
  "url": "https://github.com/darrenmcguff-GRC/ai-companion",
  "readme": "https://raw.githubusercontent.com/darrenmcguff-GRC/ai-companion/main/README.md"
}